{"sha_to_metrics": {"70eee1980346f69787e81617823b953b67afa0f7": {"_error": "Command '['python3', '-m', 'lizard', '/tmp/repo_snap_5_px1ghu']' timed out after 180 seconds"}, "b9888d1ec541930af9101b7ea4cc934e6cdbc65f": {"_error": "Command '['python3', '-m', 'lizard', '/tmp/repo_snap_iphijjud']' timed out after 180 seconds"}, "911b2097ae3988702d8a1f5076b3e11eecfee7d7": {"_error": "Command '['python3', '-m', 'lizard', '/tmp/repo_snap_9jkquhz4']' timed out after 180 seconds"}, "3286e7a85b65208f558233c12f9d3abd8b628d32": {"_error": "Command '['python3', '-m', 'lizard', '/tmp/repo_snap_pqr972ia']' timed out after 180 seconds"}, "04eb91e8ca5a4db33bb3e15eecf4b9634dcf11b1": {"_error": "Command '['python3', '-m', 'lizard', '/tmp/repo_snap_017x6uy6']' timed out after 180 seconds"}, "eaf33185de2e199aeddfaf2018cf0f6114544018": {"_error": "Command '['python3', '-m', 'lizard', '/tmp/repo_snap_6d4xo8ly']' timed out after 180 seconds"}, "edbae7d16da7736171e6858a199ef66600c3e9a9": {"_error": "Command '['python3', '-m', 'lizard', '/tmp/repo_snap_gzjqfg5f']' timed out after 180 seconds"}, "26c327f800a19019e3980d322ed60dc9cb169d45": {"_error": "Command '['python3', '-m', 'lizard', '/tmp/repo_snap_fqpxgm7l']' timed out after 180 seconds"}, "c71bedcb51c62816c7a8d10b5986473d38655d62": {"_error": "Command '['python3', '-m', 'lizard', '/tmp/repo_snap_5c8vj3zj']' timed out after 180 seconds"}, "ad144be54ed6f4a47682a6c8b3d8976f31f22ab0": {"_error": "Command '['python3', '-m', 'lizard', '/tmp/repo_snap_17h5vhfv']' timed out after 180 seconds"}, "f3b822209590fc67255a77108e716f225b67cdf8": {"_error": "Command '['python3', '-m', 'lizard', '/tmp/repo_snap_twocwox_']' timed out after 180 seconds"}, "1b67e1a6bbcdacbfb16d2414f4b4da8a64b66e09": {"_error": "Command '['python3', '-m', 'lizard', '/tmp/repo_snap_ypnrl4h5']' timed out after 180 seconds"}, "b104a3069548d6357750d9bc70f75d5c4673bb5b": {"_error": "Command '['python3', '-m', 'lizard', '/tmp/repo_snap_b5thsun7']' timed out after 180 seconds"}, "8fe844817e0f025d008a3bcd22203b7a54784ba8": {"_error": "Command '['python3', '-m', 'lizard', '/tmp/repo_snap_i7ztz33p']' timed out after 180 seconds"}, "17bb5043ac216ebf608c17f2fe8d3e4458bc487a": {"_error": "Command '['python3', '-m', 'lizard', '/tmp/repo_snap_ylah4vs1']' timed out after 180 seconds"}, "859c3fdc7c90262e3bf35a1d94d8093190a7eef4": {"_error": "Command '['python3', '-m', 'lizard', '/tmp/repo_snap_5sqdk1n8']' timed out after 180 seconds"}, "8cfc98d1b2cd89d638f23de948636c0f75ba0a3a": {"_error": "Command '['python3', '-m', 'lizard', '/tmp/repo_snap_ybyiwme9']' timed out after 180 seconds"}, "e0ad0b27b47b7342ef28846384cbe443f78e19ac": {"_error": "Command '['python3', '-m', 'lizard', '/tmp/repo_snap_nupzzhs8']' timed out after 180 seconds"}}}